[
  {
    "metricId": "groupCountOverlap",
    "type": "countOverlap",
    "classes": [
      {
        "classId": "mpa",
        "display": "Marine Protected Areas"
      },
      {
        "classId": "aquaculture",
        "display": "Aquaculture Areas"
      }
    ]
  },
  {
    "metricId": "boundaryAreaOverlap",
    "type": "areaOverlap",
    "classes": [
      {
        "classId": "nearshore",
        "display": "Territorial Sea",
        "datasourceId": "nearshore",
        "layerId": "f2Z9cV8d9"
      }
    ]
  },
  {
    "metricId": "ousValueOverlap",
    "type": "valueOverlap",
    "classes": [
      {
        "classId": "ous_aquaculture",
        "display": "Aquaculture",
        "datasourceId": "ous_aquaculture",
        "layerId": "t_GGIk3CD"
      },
      {
        "classId": "ous_community_recreational_use",
        "display": "Community/Recreational",
        "datasourceId": "ous_community_recreational_use",
        "layerId": "1HN8AsnYC"
      },
      {
        "classId": "ous_construction_infrastructure",
        "display": "Construction/Infrastructure",
        "datasourceId": "ous_construction_infrastructure",
        "layerId": "Bqy5Bd1gF"
      },
      {
        "classId": "ous_cultural_use",
        "display": "Cultural Use",
        "datasourceId": "ous_cultural_use",
        "layerId": "2S3RgfSVg"
      },
      {
        "classId": "ous_fisheries",
        "display": "Fisheries",
        "datasourceId": "ous_fisheries",
        "layerId": "8p_ow_c5I"
      },
      {
        "classId": "ous_maritime_activity",
        "display": "Maritime Activity",
        "datasourceId": "ous_maritime_activity",
        "layerId": "Z2Mc5AAUB"
      },
      {
        "classId": "ous_research",
        "display": "Research",
        "datasourceId": "ous_research",
        "layerId": "CnKHPiBXy"
      },
      {
        "classId": "ous_tourism",
        "display": "Tourism",
        "datasourceId": "ous_tourism",
        "layerId": "B1MC9XtEH"
      },
      {
        "classId": "ous_transportation",
        "display": "Transportation",
        "datasourceId": "ous_transportation",
        "layerId": "WqhqAjWkl"
      }
    ]
  },
  {
    "metricId": "habitatAreaOverlap",
    "type": "areaOverlap",
    "layerId": "kBre13eD_",
    "classes": [
      {
        "classKey": "class",
        "classId": "Coral/Algae",
        "display": "Coral/Algae",
        "datasourceId": "benthic"
      },
      {
        "classKey": "class",
        "classId": "Microalgal Mats",
        "display": "Microalgal Mats",
        "datasourceId": "benthic"
      },
      {
        "classKey": "class",
        "classId": "Rock",
        "display": "Rock",
        "datasourceId": "benthic"
      },
      {
        "classKey": "class",
        "classId": "Rubble",
        "display": "Rubble",
        "datasourceId": "benthic"
      },
      {
        "classKey": "class",
        "classId": "Sand",
        "display": "Sand",
        "datasourceId": "benthic"
      },
      {
        "classKey": "class",
        "classId": "Seagrass",
        "display": "Seagrass",
        "datasourceId": "benthic"
      }
    ]
  },
  {
    "metricId": "tradeoffValueOverlap",
    "type": "valueOverlap",
    "classes": [
      {
        "classId": "nearshore",
        "display": "Nearshore",
        "datasourceId": "nearshore"
      },
      {
        "classId": "benthic_tradeoff",
        "display": "Key Benthic Habitat",
        "datasourceId": "benthic",
        "layerId": "kBre13eD_"
      },
      {
        "classId": "fisheries_tradeoff",
        "display": "Fisheries",
        "datasourceId": "ous_fisheries",
        "layerId": "8p_ow_c5I"
      }
    ]
  },
  {
    "metricId": "ous",
    "type": "valueOverlap",
    "classes": [
      {
        "classId": "ous_aquaculture",
        "display": "Aquaculture",
        "datasourceId": "ous_aquaculture",
        "layerId": "t_GGIk3CD"
      },
      {
        "classId": "ous_community_recreational_use",
        "display": "Community/Recreational",
        "datasourceId": "ous_community_recreational_use",
        "layerId": "1HN8AsnYC"
      },
      {
        "classId": "ous_construction_infrastructure",
        "display": "Construction/Infrastructure",
        "datasourceId": "ous_construction_infrastructure",
        "layerId": "Bqy5Bd1gF"
      },
      {
        "classId": "ous_cultural_use",
        "display": "Cultural Use",
        "datasourceId": "ous_cultural_use",
        "layerId": "2S3RgfSVg"
      },
      {
        "classId": "ous_fisheries",
        "display": "Fisheries",
        "datasourceId": "ous_fisheries",
        "layerId": "8p_ow_c5I"
      },
      {
        "classId": "ous_maritime_activity",
        "display": "Maritime Activity",
        "datasourceId": "ous_maritime_activity",
        "layerId": "Z2Mc5AAUB"
      },
      {
        "classId": "ous_research",
        "display": "Research",
        "datasourceId": "ous_research",
        "layerId": "CnKHPiBXy"
      },
      {
        "classId": "ous_tourism",
        "display": "Tourism",
        "datasourceId": "ous_tourism",
        "layerId": "B1MC9XtEH"
      },
      {
        "classId": "ous_transportation",
        "display": "Transportation",
        "datasourceId": "ous_transportation",
        "layerId": "WqhqAjWkl"
      }
    ]
  },
  {
    "metricId": "habitatTest",
    "type": "areaOverlap",
    "layerId": "kBre13eD_",
    "classes": [
      {
        "classKey": "class",
        "classId": "Coral/Algae",
        "display": "Coral/Algae",
        "datasourceId": "benthic"
      },
      {
        "classKey": "class",
        "classId": "Microalgal Mats",
        "display": "Microalgal Mats",
        "datasourceId": "benthic"
      },
      {
        "classKey": "class",
        "classId": "Rock",
        "display": "Rock",
        "datasourceId": "benthic"
      },
      {
        "classKey": "class",
        "classId": "Rubble",
        "display": "Rubble",
        "datasourceId": "benthic"
      },
      {
        "classKey": "class",
        "classId": "Sand",
        "display": "Sand",
        "datasourceId": "benthic"
      },
      {
        "classKey": "class",
        "classId": "Seagrass",
        "display": "Seagrass",
        "datasourceId": "benthic"
      }
    ]
  },
  {
    "metricId": "ousOverallDemographicOverlap",
    "type": "countOverlap",
    "classes": [
      {
        "classId": "ousPeopleCount_all",
        "display": "Total",
        "datasourceId": "ous_demographics.fgb",
        "layerId": ""
      }
    ]
  },
  {
    "metricId": "ousSectorDemographicOverlap",
    "type": "countOverlap",
    "classes": [
      {
        "classId": "Fisheries",
        "display": "Fisheries",
        "datasourceId": "ous_demographics.fgb",
        "layerId": ""
      },
      {
        "classId": "Aquaculture",
        "display": "Aquaculture",
        "datasourceId": "ous_demographics.fgb",
        "layerId": ""
      },
      {
        "classId": "Community Recreational Use",
        "display": "Community Recreational Use",
        "datasourceId": "ous_demographics.fgb",
        "layerId": ""
      },
      {
        "classId": "Cultural Use",
        "display": "Cultural Use",
        "datasourceId": "ous_demographics.fgb",
        "layerId": ""
      },
      {
        "classId": "Research / Data Collection",
        "display": "Research / Data Collection",
        "datasourceId": "ous_demographics.fgb",
        "layerId": ""
      },
      {
        "classId": "Tourism",
        "display": "Tourism",
        "datasourceId": "ous_demographics.fgb",
        "layerId": ""
      },
      {
        "classId": "Transportation",
        "display": "Transportation",
        "datasourceId": "ous_demographics.fgb",
        "layerId": ""
      },
      {
        "classId": "Maritime Activity",
        "display": "Maritime Activity",
        "datasourceId": "ous_demographics.fgb",
        "layerId": ""
      },
      {
        "classId": "Construction and Infrastructure",
        "display": "Construction and Infrastructure",
        "datasourceId": "ous_demographics.fgb",
        "layerId": ""
      }
    ]
  },
  {
    "metricId": "ousMunicipalityDemographicOverlap",
    "type": "countOverlap",
    "classes": [
      {
        "classId": "Lelu",
        "display": "Lelu",
        "datasourceId": "ous_demographics.fgb",
        "layerId": ""
      },
      {
        "classId": "Malem",
        "display": "Malem",
        "datasourceId": "ous_demographics.fgb",
        "layerId": ""
      },
      {
        "classId": "Tafunsak",
        "display": "Tafunsak",
        "datasourceId": "ous_demographics.fgb",
        "layerId": ""
      },
      {
        "classId": "Utwe",
        "display": "Utwe",
        "datasourceId": "ous_demographics.fgb",
        "layerId": ""
      },
      {
        "classId": "Walung",
        "display": "Walung",
        "datasourceId": "ous_demographics.fgb",
        "layerId": ""
      },
      {
        "classId": "unknown-municipality",
        "display": "Unknown",
        "datasourceId": "ous_demographics.fgb",
        "layerId": ""
      }
    ]
  },
  {
    "metricId": "ousGearDemographicOverlap",
    "type": "countOverlap",
    "classes": [
      {
        "classId": "Bottom Fishing",
        "display": "Bottom Fishing",
        "datasourceId": "ous_demographics.fgb",
        "layerId": ""
      },
      {
        "classId": "Cast Net",
        "display": "Cast Net",
        "datasourceId": "ous_demographics.fgb",
        "layerId": ""
      },
      {
        "classId": "Casting",
        "display": "Casting",
        "datasourceId": "ous_demographics.fgb",
        "layerId": ""
      },
      {
        "classId": "Gathering / Reef Gleaning",
        "display": "Gathering / Reef Gleaning",
        "datasourceId": "ous_demographics.fgb",
        "layerId": ""
      },
      {
        "classId": "Other(Torch fishing)",
        "display": "Other(Torch fishing)",
        "datasourceId": "ous_demographics.fgb",
        "layerId": ""
      },
      {
        "classId": "Spear/Harpoon",
        "display": "Spear/Harpoon",
        "datasourceId": "ous_demographics.fgb",
        "layerId": ""
      },
      {
        "classId": "Trap / Fish Fence / Gill Net",
        "display": "Trap / Fish Fence / Gill Net",
        "datasourceId": "ous_demographics.fgb",
        "layerId": ""
      },
      {
        "classId": "Trolling",
        "display": "Trolling",
        "datasourceId": "ous_demographics.fgb",
        "layerId": ""
      },
      {
        "classId": "Vertical Longline",
        "display": "Vertical Longline",
        "datasourceId": "ous_demographics.fgb",
        "layerId": ""
      }
    ]
  }
]
